quark_plugin_mqss/__init__.py
quark_plugin_mqss/circuit_provider.py
quark_plugin_mqss/job_execution.py
quark_plugin_mqss-0.2.0.dist-info/licenses/LICENSE
quark_plugin_mqss-0.2.0.dist-info/licenses/NOTICE
quark_plugin_mqss-0.2.0.dist-info/METADATA
quark_plugin_mqss-0.2.0.dist-info/WHEEL
quark_plugin_mqss-0.2.0.dist-info/top_level.txt
quark_plugin_mqss-0.2.0.dist-info/RECORD
